dask_gateway/__init__.py
dask_gateway/_version.py
dask_gateway/auth.py
dask_gateway/client.py
dask_gateway/comm.py
dask_gateway/config.py
dask_gateway/gateway.yaml
dask_gateway/options.py
dask_gateway/scheduler_preload.py
dask_gateway/utils.py
dask_gateway-2025.4.0.dist-info/METADATA
dask_gateway-2025.4.0.dist-info/WHEEL
dask_gateway-2025.4.0.dist-info/licenses/LICENSE
dask_gateway-2025.4.0.dist-info/RECORD
