Metadata-Version: 2.4
Name: dask-gateway
Version: 2025.4.0
Summary: A client library for interacting with a dask-gateway server
Project-URL: Documentation, https://gateway.dask.org/
Project-URL: Source, https://github.com/dask/dask-gateway/
Project-URL: Issues, https://github.com/dask/dask-gateway/issues
Author-email: Jim Crist-Harif <jcristharif@gmail.com>
License: Copyright (c) 2019, Jim Crist-Harif
License-File: LICENSE
Keywords: HPC,cluster,dask,distributed,hadoop,kubernetes
Classifier: Development Status :: 5 - Production/Stable
Classifier: Intended Audience :: Developers
Classifier: Intended Audience :: Science/Research
Classifier: License :: OSI Approved :: BSD License
Classifier: Programming Language :: Python :: 3
Classifier: Topic :: Scientific/Engineering
Classifier: Topic :: System :: Distributed Computing
Requires-Python: >=3.10
Requires-Dist: aiohttp
Requires-Dist: click>=8.1.3
Requires-Dist: dask>=2022.4.0
Requires-Dist: distributed>=2022.4.0
Requires-Dist: pyyaml
Requires-Dist: tornado
Provides-Extra: kerberos
Requires-Dist: pykerberos; (platform_system != 'Windows') and extra == 'kerberos'
Requires-Dist: winkerberos; (platform_system == 'Windows') and extra == 'kerberos'
